{
  "fetchedAt": "2026-06-08T08:16:14.379Z",
  "posts": [
    {
      "title": "Free Food/Laundry/Shower Resources in HRM - June 2026",
      "score": 0,
      "numComments": 0,
      "author": "maximumice",
      "url": "https://www.reddit.com/r/halifax/comments/1twvwry/free_foodlaundryshower_resources_in_hrm_june_2026/",
      "flair": null,
      "createdUtc": 1780597130
    },
    {
      "title": "Things To Do In HRM This Month — June, 2026",
      "score": 0,
      "numComments": 0,
      "author": "AutoModerator",
      "url": "https://www.reddit.com/r/halifax/comments/1ttnjoh/things_to_do_in_hrm_this_month_june_2026/",
      "flair": null,
      "createdUtc": 1780308058
    },
    {
      "title": "Petition to stop opening cookie chains and give us a Chipotle.",
      "score": 0,
      "numComments": 0,
      "author": "ResidentMonk4063",
      "url": "https://www.reddit.com/r/halifax/comments/1tzmup0/petition_to_stop_opening_cookie_chains_and_give/",
      "flair": null,
      "createdUtc": 1780863518
    },
    {
      "title": "Sullivan's Pond gosling update",
      "score": 0,
      "numComments": 0,
      "author": "cache_invalidation",
      "url": "https://www.reddit.com/r/halifax/comments/1tzv14m/sullivans_pond_gosling_update/",
      "flair": null,
      "createdUtc": 1780884982
    },
    {
      "title": "Found a box we hadn't unpacked since we got married",
      "score": 0,
      "numComments": 0,
      "author": "shitposter1000",
      "url": "https://www.reddit.com/r/halifax/comments/1tzmahn/found_a_box_we_hadnt_unpacked_since_we_got_married/",
      "flair": null,
      "createdUtc": 1780862229
    },
    {
      "title": "Canadian Karen freakout",
      "score": 0,
      "numComments": 0,
      "author": "Techito",
      "url": "https://www.reddit.com/r/halifax/comments/1tza1h1/canadian_karen_freakout/",
      "flair": null,
      "createdUtc": 1780832992
    },
    {
      "title": "Spring Garden Road Safety?",
      "score": 0,
      "numComments": 0,
      "author": "simpleblissss",
      "url": "https://www.reddit.com/r/halifax/comments/1tzo9ik/spring_garden_road_safety/",
      "flair": null,
      "createdUtc": 1780866848
    },
    {
      "title": "Hal-Con Medieval Market",
      "score": 0,
      "numComments": 0,
      "author": "TheLifemakers",
      "url": "https://www.reddit.com/r/halifax/comments/1tzrfq3/halcon_medieval_market/",
      "flair": null,
      "createdUtc": 1780874934
    },
    {
      "title": "Cold blob",
      "score": 0,
      "numComments": 0,
      "author": "GettingHygge",
      "url": "https://www.reddit.com/r/halifax/comments/1tzs9he/cold_blob/",
      "flair": null,
      "createdUtc": 1780877173
    },
    {
      "title": "Stop the BTK Spray in Pollets Cove/Pleasant Bay!",
      "score": 0,
      "numComments": 0,
      "author": "Material-Ad-3523",
      "url": "https://www.reddit.com/r/halifax/comments/1tztsra/stop_the_btk_spray_in_pollets_covepleasant_bay/",
      "flair": null,
      "createdUtc": 1780881453
    },
    {
      "title": "Unbelievable Growth: This North American Airport Has 40% More Transatlantic Flights This Summer",
      "score": 0,
      "numComments": 0,
      "author": "No_Magazine9625",
      "url": "https://www.reddit.com/r/halifax/comments/1tzicgo/unbelievable_growth_this_north_american_airport/",
      "flair": null,
      "createdUtc": 1780853437
    },
    {
      "title": "Halifax Pride, worth going?",
      "score": 0,
      "numComments": 0,
      "author": "Electronic-Ad-8753",
      "url": "https://www.reddit.com/r/halifax/comments/1tzuqmp/halifax_pride_worth_going/",
      "flair": null,
      "createdUtc": 1780884135
    },
    {
      "title": "Canadian Baseball League pitching Nova Scotia on franchise opportunity",
      "score": 0,
      "numComments": 0,
      "author": "insino93",
      "url": "https://www.reddit.com/r/halifax/comments/1tzfci5/canadian_baseball_league_pitching_nova_scotia_on/",
      "flair": null,
      "createdUtc": 1780846562
    },
    {
      "title": "CBC's Turtle Soup (Lost Media)",
      "score": 0,
      "numComments": 0,
      "author": "BetamaxKing",
      "url": "https://www.reddit.com/r/halifax/comments/1tzff54/cbcs_turtle_soup_lost_media/",
      "flair": null,
      "createdUtc": 1780846729
    },
    {
      "title": "Fist Time to Halifax Pride.",
      "score": 0,
      "numComments": 0,
      "author": "Bulky_Organization94",
      "url": "https://www.reddit.com/r/halifax/comments/1tzer55/fist_time_to_halifax_pride/",
      "flair": null,
      "createdUtc": 1780845177
    },
    {
      "title": "Halifax Parks - The good the bad and the ugly",
      "score": 0,
      "numComments": 0,
      "author": "Proper_Ad2045",
      "url": "https://www.reddit.com/r/halifax/comments/1tz8jy6/halifax_parks_the_good_the_bad_and_the_ugly/",
      "flair": null,
      "createdUtc": 1780828193
    },
    {
      "title": "Did you lose cash outside Sobeys Queen Street yesterday?",
      "score": 0,
      "numComments": 0,
      "author": "EarthSignificant4354",
      "url": "https://www.reddit.com/r/halifax/comments/1tzagpn/did_you_lose_cash_outside_sobeys_queen_street/",
      "flair": null,
      "createdUtc": 1780834247
    },
    {
      "title": "Emergency Dental",
      "score": 0,
      "numComments": 0,
      "author": "jedaffra",
      "url": "https://www.reddit.com/r/halifax/comments/1tzt9t3/emergency_dental/",
      "flair": null,
      "createdUtc": 1780879956
    },
    {
      "title": "Tiny giants: Why Nova Scotia Honeycrisp apples appear smaller right now",
      "score": 0,
      "numComments": 0,
      "author": "Street_Anon",
      "url": "https://www.reddit.com/r/halifax/comments/1tzaa8a/tiny_giants_why_nova_scotia_honeycrisp_apples/",
      "flair": null,
      "createdUtc": 1780833708
    },
    {
      "title": "Labatt 50",
      "score": 0,
      "numComments": 0,
      "author": "AhMr1",
      "url": "https://www.reddit.com/r/halifax/comments/1tzlxv5/labatt_50/",
      "flair": null,
      "createdUtc": 1780861414
    },
    {
      "title": "Looking for peach nectarine redbull s",
      "score": 0,
      "numComments": 0,
      "author": "DenseRegret4444",
      "url": "https://www.reddit.com/r/halifax/comments/1tzuac7/looking_for_peach_nectarine_redbull_s/",
      "flair": null,
      "createdUtc": 1780882855
    },
    {
      "title": "Violin luthier from 1977",
      "score": 0,
      "numComments": 0,
      "author": "i-recycle-pubi-hair",
      "url": "https://www.reddit.com/r/halifax/comments/1tzm1vl/violin_luthier_from_1977/",
      "flair": null,
      "createdUtc": 1780861673
    },
    {
      "title": "Anyone lose a key near Young and Novalea?",
      "score": 0,
      "numComments": 0,
      "author": "annekenzie",
      "url": "https://www.reddit.com/r/halifax/comments/1tzivb7/anyone_lose_a_key_near_young_and_novalea/",
      "flair": null,
      "createdUtc": 1780854619
    },
    {
      "title": "instant loans in the city",
      "score": 0,
      "numComments": 0,
      "author": "O-Zone64",
      "url": "https://www.reddit.com/r/halifax/comments/1tzxwja/instant_loans_in_the_city/",
      "flair": null,
      "createdUtc": 1780893663
    },
    {
      "title": "Tips for lawn levelling/topdressing in Halifax?",
      "score": 0,
      "numComments": 0,
      "author": "lIlIIIIlllIIlIIIllll",
      "url": "https://www.reddit.com/r/halifax/comments/1tzg83m/tips_for_lawn_levellingtopdressing_in_halifax/",
      "flair": null,
      "createdUtc": 1780848580
    },
    {
      "title": "Coastal Wall Paintings/Decor?",
      "score": 0,
      "numComments": 0,
      "author": "Arm-Complex",
      "url": "https://www.reddit.com/r/halifax/comments/1tzlzmt/coastal_wall_paintingsdecor/",
      "flair": null,
      "createdUtc": 1780861530
    },
    {
      "title": "Naturopathic doctors now a regulated profession in Nova Scotia",
      "score": 0,
      "numComments": 0,
      "author": "toneyriver12",
      "url": "https://www.reddit.com/r/halifax/comments/1tyv9fw/naturopathic_doctors_now_a_regulated_profession/",
      "flair": null,
      "createdUtc": 1780786209
    },
    {
      "title": "Does anyone know where i can buy traditional kajal or kohl eyeliner?",
      "score": 0,
      "numComments": 0,
      "author": "Pawssabillitysawait",
      "url": "https://www.reddit.com/r/halifax/comments/1tzti55/does_anyone_know_where_i_can_buy_traditional/",
      "flair": null,
      "createdUtc": 1780880618
    },
    {
      "title": "Regatta Point / Spinnaker condos / 80’s era condos",
      "score": 0,
      "numComments": 0,
      "author": "Pristine-Network1",
      "url": "https://www.reddit.com/r/halifax/comments/1tzmln5/regatta_point_spinnaker_condos_80s_era_condos/",
      "flair": null,
      "createdUtc": 1780862937
    },
    {
      "title": "Missing Keys",
      "score": 0,
      "numComments": 0,
      "author": "reddingjoe",
      "url": "https://www.reddit.com/r/halifax/comments/1tzhoe2/missing_keys/",
      "flair": null,
      "createdUtc": 1780851913
    }
  ]
}