{
  "fetchedAt": "2026-06-22T15:30:18.895Z",
  "posts": [
    {
      "title": "Free Food/Laundry/Shower Resources in HRM - June 2026",
      "score": 0,
      "numComments": 0,
      "author": "maximumice",
      "url": "https://www.reddit.com/r/halifax/comments/1twvwry/free_foodlaundryshower_resources_in_hrm_june_2026/",
      "flair": null,
      "createdUtc": 1780597130
    },
    {
      "title": "Things To Do In HRM This Month — June, 2026",
      "score": 0,
      "numComments": 0,
      "author": "AutoModerator",
      "url": "https://www.reddit.com/r/halifax/comments/1ttnjoh/things_to_do_in_hrm_this_month_june_2026/",
      "flair": null,
      "createdUtc": 1780308058
    },
    {
      "title": "Neoliner Origin",
      "score": 0,
      "numComments": 0,
      "author": "HalifaxReTales",
      "url": "https://www.reddit.com/r/halifax/comments/1uchx50/neoliner_origin/",
      "flair": null,
      "createdUtc": 1782127498
    },
    {
      "title": "Baseball association cries foul over HRM proposal to convert field for cricket",
      "score": 0,
      "numComments": 0,
      "author": "Injustice_For_All_",
      "url": "https://www.reddit.com/r/halifax/comments/1ucful4/baseball_association_cries_foul_over_hrm_proposal/",
      "flair": null,
      "createdUtc": 1782120626
    },
    {
      "title": "Found ring",
      "score": 0,
      "numComments": 0,
      "author": "DSP902",
      "url": "https://www.reddit.com/r/halifax/comments/1uclsoy/found_ring/",
      "flair": null,
      "createdUtc": 1782137799
    },
    {
      "title": "Defence boom could put pressure on Halifax's housing market, infrastructure",
      "score": 0,
      "numComments": 0,
      "author": "insino93",
      "url": "https://www.reddit.com/r/halifax/comments/1uchjeh/defence_boom_could_put_pressure_on_halifaxs/",
      "flair": null,
      "createdUtc": 1782126269
    },
    {
      "title": "Is it Eat the Rich or Glaze the Rich?",
      "score": 0,
      "numComments": 0,
      "author": "Upbeat_Letterhead937",
      "url": "https://www.reddit.com/r/halifax/comments/1ubytsy/is_it_eat_the_rich_or_glaze_the_rich/",
      "flair": null,
      "createdUtc": 1782069975
    },
    {
      "title": "Spotted This Beauty Today! Haven't spotted one in a few years.",
      "score": 0,
      "numComments": 0,
      "author": "HFXmer",
      "url": "https://www.reddit.com/r/halifax/comments/1uc0yl1/spotted_this_beauty_today_havent_spotted_one_in_a/",
      "flair": null,
      "createdUtc": 1782075220
    },
    {
      "title": "Went to our sister city Hakodate",
      "score": 0,
      "numComments": 0,
      "author": "AmbitiousEngine7444",
      "url": "https://www.reddit.com/r/halifax/comments/1ubyanl/went_to_our_sister_city_hakodate/",
      "flair": null,
      "createdUtc": 1782068691
    },
    {
      "title": "Overhauls and upgrades to Halifax Transit ferries, terminals will cost almost $45 million",
      "score": 0,
      "numComments": 0,
      "author": "Injustice_For_All_",
      "url": "https://www.reddit.com/r/halifax/comments/1ucj5py/overhauls_and_upgrades_to_halifax_transit_ferries/",
      "flair": null,
      "createdUtc": 1782131149
    },
    {
      "title": "SailGP Team Canada posing at the Halifax Waterfont.",
      "score": 0,
      "numComments": 0,
      "author": "gps527",
      "url": "https://www.reddit.com/r/halifax/comments/1ucan1l/sailgp_team_canada_posing_at_the_halifax_waterfont/",
      "flair": null,
      "createdUtc": 1782102327
    },
    {
      "title": "Seeking peanut brittle",
      "score": 0,
      "numComments": 0,
      "author": "Ordinary-Review-3819",
      "url": "https://www.reddit.com/r/halifax/comments/1ucm0o6/seeking_peanut_brittle/",
      "flair": null,
      "createdUtc": 1782138301
    },
    {
      "title": "Beautiful Day at Polly’s Cove",
      "score": 0,
      "numComments": 0,
      "author": "crwpitman",
      "url": "https://www.reddit.com/r/halifax/comments/1ubwewi/beautiful_day_at_pollys_cove/",
      "flair": null,
      "createdUtc": 1782064203
    },
    {
      "title": "D&D Signups! The Chronicles of Cadilon",
      "score": 0,
      "numComments": 0,
      "author": "thedeckboxhalifax",
      "url": "https://www.reddit.com/r/halifax/comments/1ucm0mk/dd_signups_the_chronicles_of_cadilon/",
      "flair": null,
      "createdUtc": 1782138298
    },
    {
      "title": "SailGP 2026 photos",
      "score": 0,
      "numComments": 0,
      "author": "GEF110F14F15",
      "url": "https://www.reddit.com/r/halifax/comments/1uc3uaq/sailgp_2026_photos/",
      "flair": null,
      "createdUtc": 1782082724
    },
    {
      "title": "Local Horror Writing",
      "score": 0,
      "numComments": 0,
      "author": "Dancinghelix0451",
      "url": "https://www.reddit.com/r/halifax/comments/1uckjm0/local_horror_writing/",
      "flair": null,
      "createdUtc": 1782134755
    },
    {
      "title": "Man missing from Hillsborough Hospital spotted in Halifax: Charlottetown police",
      "score": 0,
      "numComments": 0,
      "author": "insino93",
      "url": "https://www.reddit.com/r/halifax/comments/1uchuts/man_missing_from_hillsborough_hospital_spotted_in/",
      "flair": null,
      "createdUtc": 1782127287
    },
    {
      "title": "City Asks Homeowner to Cut Overgrown Grass - Bulldozes Yard Instead",
      "score": 0,
      "numComments": 0,
      "author": "I-AM-PENGUIN",
      "url": "https://www.reddit.com/r/halifax/comments/1uc1g0j/city_asks_homeowner_to_cut_overgrown_grass/",
      "flair": null,
      "createdUtc": 1782076452
    },
    {
      "title": "Shout out to Hungry Hut",
      "score": 0,
      "numComments": 0,
      "author": "VeterinarianProud644",
      "url": "https://www.reddit.com/r/halifax/comments/1uc300z/shout_out_to_hungry_hut/",
      "flair": null,
      "createdUtc": 1782080434
    },
    {
      "title": "Pic from yesterday",
      "score": 0,
      "numComments": 0,
      "author": "BuddhameetsEinstein",
      "url": "https://www.reddit.com/r/halifax/comments/1uc2pk4/pic_from_yesterday/",
      "flair": null,
      "createdUtc": 1782079681
    },
    {
      "title": "Why the headless deceased birds??",
      "score": 0,
      "numComments": 0,
      "author": "birdiebird31",
      "url": "https://www.reddit.com/r/halifax/comments/1ucn8l8/why_the_headless_deceased_birds/",
      "flair": null,
      "createdUtc": 1782141033
    },
    {
      "title": "Grumblemania Monday",
      "score": 0,
      "numComments": 0,
      "author": "AutoModerator",
      "url": "https://www.reddit.com/r/halifax/comments/1ucgde8/grumblemania_monday/",
      "flair": null,
      "createdUtc": 1782122466
    },
    {
      "title": "SailGP Day 2 ⛵️",
      "score": 0,
      "numComments": 0,
      "author": "knifeshoes24",
      "url": "https://www.reddit.com/r/halifax/comments/1ubuxuz/sailgp_day_2/",
      "flair": null,
      "createdUtc": 1782060694
    },
    {
      "title": "Sackville River Trail",
      "score": 0,
      "numComments": 0,
      "author": "crwpitman",
      "url": "https://www.reddit.com/r/halifax/comments/1ubwhsz/sackville_river_trail/",
      "flair": null,
      "createdUtc": 1782064391
    },
    {
      "title": "HalCon has outgrown the Nova Center in the current 3-day format",
      "score": 0,
      "numComments": 0,
      "author": "Weary-Stick-3010",
      "url": "https://www.reddit.com/r/halifax/comments/1ubp6k1/halcon_has_outgrown_the_nova_center_in_the/",
      "flair": null,
      "createdUtc": 1782045999
    },
    {
      "title": "Garlicy chicken shawarma??",
      "score": 0,
      "numComments": 0,
      "author": "eseses20",
      "url": "https://www.reddit.com/r/halifax/comments/1uc3u9e/garlicy_chicken_shawarma/",
      "flair": null,
      "createdUtc": 1782082721
    },
    {
      "title": "What is this vessel?",
      "score": 0,
      "numComments": 0,
      "author": "MamaJa2016",
      "url": "https://www.reddit.com/r/halifax/comments/1uc2nkt/what_is_this_vessel/",
      "flair": null,
      "createdUtc": 1782079545
    },
    {
      "title": "I see your fancy garden walls.. and I’m jealous",
      "score": 0,
      "numComments": 0,
      "author": "deansthumbs",
      "url": "https://www.reddit.com/r/halifax/comments/1uc2yga/i_see_your_fancy_garden_walls_and_im_jealous/",
      "flair": null,
      "createdUtc": 1782080325
    },
    {
      "title": "National cannabis organization suspends operations, citing active illegal market",
      "score": 0,
      "numComments": 0,
      "author": "Injustice_For_All_",
      "url": "https://www.reddit.com/r/halifax/comments/1ucmrdk/national_cannabis_organization_suspends/",
      "flair": null,
      "createdUtc": 1782139996
    },
    {
      "title": "Pride celebrations expanding in the Maritimes this year in face of online backlash",
      "score": 0,
      "numComments": 0,
      "author": "IStillListenToRadio",
      "url": "https://www.reddit.com/r/halifax/comments/1ubm0ib/pride_celebrations_expanding_in_the_maritimes/",
      "flair": null,
      "createdUtc": 1782035416
    }
  ]
}